README.md
setup.py
luckyweb/__init__.py
luckyweb/blocks.py
luckyweb/server.py
luckyweb/version.py
luckyweb.egg-info/PKG-INFO
luckyweb.egg-info/SOURCES.txt
luckyweb.egg-info/dependency_links.txt
luckyweb.egg-info/top_level.txt
luckyweb/templates/a.tpl
luckyweb/templates/card.tpl
luckyweb/templates/form.tpl
luckyweb/templates/grid.tpl
luckyweb/templates/head.tpl
luckyweb/templates/html.tpl
luckyweb/templates/img.tpl
luckyweb/templates/list.tpl
luckyweb/templates/navbar.tpl
luckyweb/templates/p.tpl
luckyweb/templates/pagination.tpl
luckyweb/templates/table.tpl