Metadata-Version: 1.0
Name: luckyweb
Version: 1.0.0.post0
Summary: web framework for python3
Home-page: https://bxtkezhan.github.io/luckyweb
Author: bxtkezhan-kk
Author-email: bxtkezhan@gmail.com
License: MIT License
Keywords: lucky web
Platform: UNKNOWN
